unshell/__init__.py
unshell/cli.py
unshell/core.py
unshell/py.typed
unshell/test_cli.py
unshell/test_core.py
unshell/type.py
unshell/utils/__init__.py
unshell/utils/colors.py
unshell/utils/pipe.py
unshell/utils/test_colors.py
unshell/utils/test_pipe.py
unshell-0.7.0.dist-info/LICENSE.md
unshell-0.7.0.dist-info/WHEEL
unshell-0.7.0.dist-info/METADATA
unshell-0.7.0.dist-info/RECORD
