Metadata-Version: 2.1
Name: unshell
Version: 0.7.0
Summary: Set your shell free !
Home-page: https://github.com/romainPrignon/unshellPy
License: MIT
Keywords: shell subprocess scripting
Author: Romain Prignon
Author-email: pro.rprignon@gmail.com
Requires-Python: >=3.8.5,<4.0.0
Classifier: License :: OSI Approved :: MIT License
Classifier: Programming Language :: Python :: 3
Classifier: Programming Language :: Python :: 3.10
Classifier: Programming Language :: Python :: 3.9
Project-URL: Repository, https://github.com/romainPrignon/unshellPy
